ourtieba/__init__.py
ourtieba/database.py
ourtieba/logger.py
ourtieba/scheduler.py
ourtieba/scrapper.py
ourtieba/configs/__init__.py
ourtieba/configs/config.py
ourtieba/configs/functions.py
ourtieba/configs/macros.py
ourtieba/models/__init__.py
ourtieba/models/_tables.py
ourtieba/models/admin.py
ourtieba/models/board.py
ourtieba/models/comment.py
ourtieba/models/comment_status.py
ourtieba/models/notification.py
ourtieba/models/post.py
ourtieba/models/post_status.py
ourtieba/models/report.py
ourtieba/models/subscription.py
ourtieba/models/user.py
ourtieba/models/view_history.py
ourtieba/static/css/bootstrap.min.css
ourtieba/static/css/fullpage.min.css
ourtieba/static/css/fullpage.min.css.map
ourtieba/static/css/signin.css
ourtieba/static/ico/favicon.ico
ourtieba/static/img/logo.png
ourtieba/static/js/DPlayer.min.js
ourtieba/static/js/DPlayer.min.js.map
ourtieba/static/js/bootstrap.min.js
ourtieba/static/js/fullpage.min.js
ourtieba/static/js/fullpage.min.js.map
ourtieba/static/js/get_log.js
ourtieba/static/js/jquery-3.6.0.min.js
ourtieba/static/js/main.js
ourtieba/static/ueditor/config.json
ourtieba/static/ueditor/ueditor.all.js
ourtieba/static/ueditor/ueditor.all.min.js
ourtieba/static/ueditor/ueditor.config.js
ourtieba/static/ueditor/dialogs/internal.js
ourtieba/static/ueditor/dialogs/emotion/emotion.html
ourtieba/static/ueditor/dialogs/image/image.css
ourtieba/static/ueditor/dialogs/image/image.html
ourtieba/static/ueditor/dialogs/image/image.js
ourtieba/static/ueditor/dialogs/image/images/alignicon.jpg
ourtieba/static/ueditor/dialogs/image/images/bg.png
ourtieba/static/ueditor/dialogs/image/images/icons.gif
ourtieba/static/ueditor/dialogs/image/images/icons.png
ourtieba/static/ueditor/dialogs/image/images/image.png
ourtieba/static/ueditor/dialogs/image/images/progress.png
ourtieba/static/ueditor/dialogs/image/images/success.gif
ourtieba/static/ueditor/dialogs/image/images/success.png
ourtieba/static/ueditor/dialogs/link/link.html
ourtieba-0.1.0.dist-info/LICENSE
ourtieba-0.1.0.dist-info/METADATA
ourtieba-0.1.0.dist-info/WHEEL
ourtieba-0.1.0.dist-info/top_level.txt
ourtieba-0.1.0.dist-info/RECORD
